lib/__init__.py
lib/shreya.py
Topsis_shreya_102203070-0.0.1.dist-info/METADATA
Topsis_shreya_102203070-0.0.1.dist-info/WHEEL
Topsis_shreya_102203070-0.0.1.dist-info/top_level.txt
Topsis_shreya_102203070-0.0.1.dist-info/RECORD
